{  
    "carSpeedData" : [
        { "spd" : 1.0 , "kill" : 0 } ,
        { "spd" : 1.05 , "kill" : 10 } ,
        { "spd" : 1.1 , "kill" : 30 } ,
        { "spd" : 1.15 , "kill" : 60 } ,
        { "spd" : 1.2 , "kill" : 100 } ,
        { "spd" : 1.25 , "kill" : 150 } ,
        { "spd" : 1.3 , "kill" : 210 } ,
        { "spd" : 1.35 , "kill" : 280 } ,
        { "spd" : 1.4 , "kill" : 360 } ,
        { "spd" : 1.45 , "kill" : 450 } ,
        { "spd" : 1.5 , "kill" : 550 } ,
        { "spd" : 1.55 , "kill" : 660 } ,
        { "spd" : 1.6 , "kill" : 780 } ,
        { "spd" : 1.65 , "kill" : 910 } ,
        { "spd" : 1.7 , "kill" : 1050 } ,
        { "spd" : 1.75 , "kill" : 1200 } ,
        { "spd" : 1.8 , "kill" : 1360 } ,
        { "spd" : 1.85 , "kill" : 1530 } ,
        { "spd" : 1.9 , "kill" : 1710 } ,
        { "spd" : 1.95 , "kill" : 1900 } ,
        { "spd" : 2.0 , "kill" : 2100 } ,
        { "spd" : 2.05 , "kill" : 2310 } ,
        { "spd" : 2.1 , "kill" : 2530 } ,
        { "spd" : 2.15 , "kill" : 2760 } ,
        { "spd" : 2.2 , "kill" : 3000 } ,
        { "spd" : 2.25 , "kill" : 3250 } ,
        { "spd" : 2.3 , "kill" : 3510 } ,
        { "spd" : 2.35 , "kill" : 3780 } ,
        { "spd" : 2.4 , "kill" : 4060 } ,
        { "spd" : 2.45 , "kill" : 4350 } ,
        { "spd" : 2.5 , "kill" : 4650 } ,
        { "spd" : 2.55 , "kill" : 4960 } ,
        { "spd" : 2.6 , "kill" : 5280 } ,
        { "spd" : 2.65 , "kill" : 5610 } ,
        { "spd" : 2.7 , "kill" : 5950 } ,
        { "spd" : 2.75 , "kill" : 6300 } ,
        { "spd" : 2.8 , "kill" : 6660 } ,
        { "spd" : 2.85 , "kill" : 7030 } ,
        { "spd" : 2.9 , "kill" : 7410 } ,
        { "spd" : 2.95 , "kill" : 7800 } ,
        { "spd" : 3.0 , "kill" : 8200 } ,
        { "spd" : 3.05 , "kill" : 8610 } ,
        { "spd" : 3.1 , "kill" : 9030 } ,
        { "spd" : 3.15 , "kill" :9460 } ,
        { "spd" : 3.2 , "kill" : 9900 } ,
        { "spd" : 3.25 , "kill" : 10350 }
    ] 
}